pywatchdog/__init__.py
pywatchdog/__main__.py
pywatchdog/ioctl.py
pywatchdog/watchdog.py
pywatchdog-1.0.0.dist-info/LICENSE
pywatchdog-1.0.0.dist-info/METADATA
pywatchdog-1.0.0.dist-info/WHEEL
pywatchdog-1.0.0.dist-info/entry_points.txt
pywatchdog-1.0.0.dist-info/top_level.txt
pywatchdog-1.0.0.dist-info/RECORD
