Metadata-Version: 2.1
Name: pywatchdog
Version: 1.0.0
Summary: Interact with a Linux watchdog driver using Python.
Home-page: https://github.com/AT0myks/pywatchdog
Author: AT0myks
Author-email: at0myks.dev@gmail.com
License: UNKNOWN
Project-URL: Bug Reports, https://github.com/AT0myks/pywatchdog/issues
Project-URL: Source, https://github.com/AT0myks/pywatchdog
Keywords: watchdog
Platform: UNKNOWN
Classifier: Development Status :: 5 - Production/Stable
Classifier: Intended Audience :: Developers
Classifier: Intended Audience :: System Administrators
Classifier: License :: OSI Approved :: GNU General Public License v2 (GPLv2)
Classifier: Operating System :: POSIX :: Linux
Classifier: Programming Language :: Python :: 3
Classifier: Programming Language :: Python :: 3 :: Only
Classifier: Programming Language :: Python :: 3.7
Classifier: Programming Language :: Python :: 3.8
Classifier: Programming Language :: Python :: 3.9
Classifier: Programming Language :: Python :: 3.10
Classifier: Topic :: Software Development :: Libraries
Classifier: Topic :: Software Development :: Libraries :: Python Modules
Classifier: Topic :: System :: Monitoring
Requires-Python: >=3.7
License-File: LICENSE
